nillanet/__init__.py
nillanet/activations.py
nillanet/copy-of-initializer.py
nillanet/copy-of-scheduler.py
nillanet/distributions.py
nillanet/initializer.py
nillanet/io.py
nillanet/loss.py
nillanet/model.py
nillanet/scheduler.py
nillanet-2.3.dist-info/METADATA
nillanet-2.3.dist-info/WHEEL
nillanet-2.3.dist-info/top_level.txt
nillanet-2.3.dist-info/RECORD
