Metadata-Version: 2.4
Name: nillanet
Version: 2.3
Summary: linear neural net
Author-email: James Smith <james.smith@rcsb.org>
Maintainer-email: James Smith <james.smith@rcsb.org>
Project-URL: Homepage, https://github.com/j-s-135/nillanet
Project-URL: Documentation, https://j-s-135.github.io/nillanet
Project-URL: Source, https://github.com/j-s-135/nillanet
Project-URL: Issues, https://github.com/j-s-135/nillanet/issues
Keywords: linear,neural net
Classifier: Programming Language :: Python :: 3
Classifier: License :: OSI Approved :: MIT License
Classifier: Operating System :: OS Independent
Requires-Python: >=3.6
Requires-Dist: numpy
Requires-Dist: scipy
Provides-Extra: dev
Requires-Dist: pytest; extra == "dev"
Requires-Dist: black; extra == "dev"
Requires-Dist: flake8; extra == "dev"
Provides-Extra: docs
Requires-Dist: sphinx; extra == "docs"
Requires-Dist: sphinx-rtd-theme; extra == "docs"
